zabbix_mcp/__init__.py
zabbix_mcp/models.py
zabbix_mcp/sentry_init.py
zabbix_mcp/server.py
zabbix_mcp/utils.py
zabbix_mcp/zabbix_client.py
zabbix_mcp/zabbix_middlewares.py
zabbix_mcp/zabbix_tools.py
zabbix_mcp-0.2.0.dist-info/METADATA
zabbix_mcp-0.2.0.dist-info/WHEEL
zabbix_mcp-0.2.0.dist-info/entry_points.txt
zabbix_mcp-0.2.0.dist-info/licenses/LICENSE
zabbix_mcp-0.2.0.dist-info/RECORD
