Metadata-Version: 2.4
Name: zabbix-mcp
Version: 0.2.0
Summary: MCP server for Zabbix management
Project-URL: Homepage, https://github.com/mhajder/zabbix-mcp
Project-URL: Repository, https://github.com/mhajder/zabbix-mcp
Project-URL: Documentation, https://github.com/mhajder/zabbix-mcp#readme
Project-URL: Issues, https://github.com/mhajder/zabbix-mcp/issues
Author: Mateusz Hajder
License: MIT License
License-File: LICENSE
Keywords: automation,management,mcp,network,server,zabbix
Classifier: Development Status :: 5 - Production/Stable
Classifier: Intended Audience :: Developers
Classifier: Intended Audience :: System Administrators
Classifier: License :: OSI Approved :: MIT License
Classifier: Programming Language :: Python :: 3 :: Only
Classifier: Programming Language :: Python :: 3.11
Classifier: Programming Language :: Python :: 3.12
Classifier: Programming Language :: Python :: 3.13
Classifier: Programming Language :: Python :: 3.14
Classifier: Topic :: System :: Networking
Classifier: Topic :: System :: Networking :: Monitoring
Classifier: Topic :: System :: Systems Administration
Classifier: Topic :: Utilities
Requires-Python: <3.15,>=3.11
Requires-Dist: fastmcp>=2.10.0
Requires-Dist: pydantic>=2.0.0
Requires-Dist: python-dotenv>=1.0.0
Requires-Dist: zabbix-utils[async]>=2.0.4
Provides-Extra: sentry
Requires-Dist: sentry-sdk>=2.43.0; extra == 'sentry'
